khidl/app.py
khidl/args.py
khidl/downloader.py
khidl/search.py
khidl/soundtrack.py
khinsider_dl-1.3.1.dist-info/licenses/LICENSE
khinsider_dl-1.3.1.dist-info/METADATA
khinsider_dl-1.3.1.dist-info/WHEEL
khinsider_dl-1.3.1.dist-info/entry_points.txt
khinsider_dl-1.3.1.dist-info/top_level.txt
khinsider_dl-1.3.1.dist-info/RECORD
