Metadata-Version: 2.4
Name: khinsider-dl
Version: 1.3.1
Summary: Download soundtracks from downloads.khinsider.com with a useful and quick CLI
Author: qwerinope
License-Expression: MIT
Project-URL: Homepage, https://github.com/qwerinope/khidl
Project-URL: Issues, https://github.com/qwerinope/khidl/issues
Project-URL: Repository, https://github.com/qwerinope/khidl.git
License-File: LICENSE
Requires-Dist: beautifulsoup4
Requires-Dist: requests
Requires-Dist: tqdm
Requires-Dist: jsonschema
Requires-Dist: prettytable
Dynamic: license-file
